PBQA/__init__.py
PBQA/db.py
PBQA/llm.py
pbqa-1.2.9.dist-info/licenses/LICENSE
pbqa-1.2.9.dist-info/METADATA
pbqa-1.2.9.dist-info/WHEEL
pbqa-1.2.9.dist-info/top_level.txt
pbqa-1.2.9.dist-info/RECORD
