Metadata-Version: 2.4
Name: PBQA
Version: 1.2.9
Summary: Pattern Based Question and Answer (PBQA) is a Python library that provides tools for querying LLMs and managing text embeddings. It combines guided generation with multi-shot prompting to improve response quality and consistency.
Home-page: https://github.com/Baagsma/PBQA
Author: Bart Haagsma
Author-email: dev.baagsma@gmail.com
Classifier: Development Status :: 3 - Alpha
Classifier: Intended Audience :: Developers
Classifier: License :: OSI Approved :: MIT License
Classifier: Programming Language :: Python :: 3
Classifier: Programming Language :: Python :: 3.9
Classifier: Programming Language :: Python :: 3.10
Classifier: Programming Language :: Python :: 3.11
Classifier: Programming Language :: Python :: 3.12
Requires-Python: >=3.9
License-File: LICENSE
Requires-Dist: PyYAML
Requires-Dist: requests
Requires-Dist: accelerate
Requires-Dist: transformers
Requires-Dist: qdrant-client
Requires-Dist: sentence-transformers
Requires-Dist: python-dotenv
Dynamic: author
Dynamic: author-email
Dynamic: classifier
Dynamic: description
Dynamic: description-content-type
Dynamic: home-page
Dynamic: license-file
Dynamic: requires-dist
Dynamic: requires-python
Dynamic: summary
